jrpystan/__init__.py
jrpystan/__version__.py
jrpystan/data/api.zip
jrpystan/data/centipedes.zip
jrpystan/data/faithful.zip
jrpystan/data/housing.zip
jrpystan/data/oxboys.zip
jrpystan/data/sideeffect.zip
jrpystan/data.py
jrpystan/vignettes.py
jrpystan-1.1.3.dist-info/METADATA
jrpystan-1.1.3.dist-info/WHEEL
jrpystan-1.1.3.dist-info/RECORD
